{
    "CN": {
        "ss_win_add.mani": {
            "file_name": "ss_win_add.mani",
            "hash": "e21e8b581c33e3ada4318380dabf8e9b",
            "version": 100
        },
        "p_1_m.ss_win.mani": {
            "file_name": "p_1_m.ss_win.mani",
            "hash": "111a78de325fbe50e018b08f141bc409",
            "version": 104
        },
        "data.arcx": {
            "file_name": "data.arcx",
            "hash": "5ff371aaff6c2d833b3fd827f0316c7a",
            "version": 100
        },
        "p_1_u.lua.arcx": {
            "file_name": "p_1_u.lua.arcx",
            "hash": "9fe61abc5921d131eeb794de0a3036e3",
            "version": 104
        },
        "data.json": {
            "file_name": "data.json",
            "hash": "fac451f4996326c442dc0f5a9bfb6558",
            "version": 100
        },
        "lua.json": {
            "file_name": "lua.json",
            "hash": "2cffc3f2ae2276a3da3d5222fe4c00c8",
            "version": 100
        },
        "ss_win.mani": {
            "file_name": "ss_win.mani",
            "hash": "cafe0f7529610173d77dcb1d5258466f",
            "version": 104
        },
        "lua.arcx": {
            "file_name": "lua.arcx",
            "hash": "7fda18bbe20fbf40ecb5e4b2fcb47960",
            "version": 100
        },
        "p_1_u.data.arcx": {
            "file_name": "p_1_u.data.arcx",
            "hash": "803ccb757f8db6ea04f0c768eee8dcbe",
            "version": 104
        }
    },
    "EN": {
        "p_1_u.data.arcx": {
            "file_name": "p_1_u.data.arcx",
            "hash": "5631d6b527576dbc609f404ebea643ba",
            "version": 103
        },
        "ss_win.mani": {
            "file_name": "ss_win.mani",
            "hash": "7acb21ee1372db7493ffad4cf1b0b0fa",
            "version": 103
        },
        "ss_win_add.mani": {
            "file_name": "ss_win_add.mani",
            "hash": "5269d21f0a612ffafaaab068599a53ae",
            "version": 99
        },
        "data.json": {
            "file_name": "data.json",
            "hash": "7b82353c3ba6046972a7d86f78f2557a",
            "version": 99
        },
        "p_1_u.lua.arcx": {
            "file_name": "p_1_u.lua.arcx",
            "hash": "d42a89c68536769a101c8f065275c7d8",
            "version": 103
        },
        "lua.arcx": {
            "file_name": "lua.arcx",
            "hash": "dbbbc73a878100fcd25cd1e06446e105",
            "version": 99
        },
        "p_1_m.ss_win.mani": {
            "file_name": "p_1_m.ss_win.mani",
            "hash": "140ed70f6c55195b975fa10727a5eef4",
            "version": 103
        },
        "lua.json": {
            "file_name": "lua.json",
            "hash": "97f8cea25527e33068cdfc24344352dd",
            "version": 99
        },
        "data.arcx": {
            "file_name": "data.arcx",
            "hash": "0704ad41a9966591d753ff44ab85443f",
            "version": 99
        }
    },
    "JP": {
        "p_2_m.ss_win.mani": {
            "file_name": "p_2_m.ss_win.mani",
            "hash": "32a15d36a3dad9941256a2900b076248",
            "version": 107
        },
        "ss_win_add.mani": {
            "file_name": "ss_win_add.mani",
            "hash": "a6fc7dd96bf9d8a7ae8a93cfbc87e416",
            "version": 102
        },
        "lua.arcx": {
            "file_name": "lua.arcx",
            "hash": "6f85ccc446d87149a7fe3a3958ce6558",
            "version": 102
        },
        "data.json": {
            "file_name": "data.json",
            "hash": "220da7baefd1d03bb363af8776e7d360",
            "version": 102
        },
        "data.arcx": {
            "file_name": "data.arcx",
            "hash": "6045c35a6ddd30cbf88b302d4f4033ab",
            "version": 102
        },
        "p_1_u.lua.arcx": {
            "file_name": "p_1_u.lua.arcx",
            "hash": "e7de011ff3467e2794bfb055bf309763",
            "version": 106
        },
        "lua.json": {
            "file_name": "lua.json",
            "hash": "557c41f9276fad649ffcbbdec436f1d6",
            "version": 102
        },
        "p_2_u.data.arcx": {
            "file_name": "p_2_u.data.arcx",
            "hash": "0ab1e774a333b36c27a213b232a2c928",
            "version": 107
        },
        "p_1_m.ss_win.mani": {
            "file_name": "p_1_m.ss_win.mani",
            "hash": "83ef8afc3355dadb6779652366a4e6a9",
            "version": 106
        },
        "p_1_u.data.arcx": {
            "file_name": "p_1_u.data.arcx",
            "hash": "aad20d772d15bdf3010e736c9ed1cd7d",
            "version": 106
        },
        "ss_win.mani": {
            "file_name": "ss_win.mani",
            "hash": "efe65ae6cc515e58e3a3b2e5e77189eb",
            "version": 107
        }
    },
    "KR": {
        "lua.json": {
            "file_name": "lua.json",
            "hash": "aae00828d616e126bf1c6efb7c6da5a9",
            "version": 104
        },
        "data.arcx": {
            "file_name": "data.arcx",
            "hash": "0545e4882213d29429997c0c9797b861",
            "version": 104
        },
        "p_1_u.lua.arcx": {
            "file_name": "p_1_u.lua.arcx",
            "hash": "74ff5cdd2cdb8a6da66dc93f57a70250",
            "version": 108
        },
        "ss_win.mani": {
            "file_name": "ss_win.mani",
            "hash": "6ac2f4eef423274a99e6f59b463e37c3",
            "version": 108
        },
        "lua.arcx": {
            "file_name": "lua.arcx",
            "hash": "92632af130b760ce799d660559ab6d28",
            "version": 104
        },
        "p_1_m.ss_win.mani": {
            "file_name": "p_1_m.ss_win.mani",
            "hash": "b868d21c6ef8fa0c08616667c0ae89a2",
            "version": 108
        },
        "data.json": {
            "file_name": "data.json",
            "hash": "6ae397cf69f59e646abeec578a15acb0",
            "version": 104
        },
        "p_1_u.data.arcx": {
            "file_name": "p_1_u.data.arcx",
            "hash": "dec0fabd5b3745dd4d95d08462863f53",
            "version": 108
        },
        "ss_win_add.mani": {
            "file_name": "ss_win_add.mani",
            "hash": "a8aaf474a3c9e9d8bb80c1c434ba5c48",
            "version": 104
        }
    },
    "TW": {
        "lua.arcx": {
            "file_name": "lua.arcx",
            "hash": "f326d5a9280f2acecb1ebb5bd10d424b",
            "version": 109
        },
        "p_1_m.ss_win.mani": {
            "file_name": "p_1_m.ss_win.mani",
            "hash": "a0934612ab3fac20083906aeee3f9dc8",
            "version": 113
        },
        "ss_win_add.mani": {
            "file_name": "ss_win_add.mani",
            "hash": "f27af2efcbdbf44842f02dc8ba4425fc",
            "version": 109
        },
        "data.arcx": {
            "file_name": "data.arcx",
            "hash": "9434cf622ae875009a9719d03e38ccab",
            "version": 109
        },
        "data.json": {
            "file_name": "data.json",
            "hash": "6773e40a06fb306e4f2b3c1ba8e7045e",
            "version": 109
        },
        "ss_win.mani": {
            "file_name": "ss_win.mani",
            "hash": "c059e6b37d08b03dafecf44206fa3d4e",
            "version": 113
        },
        "p_1_u.lua.arcx": {
            "file_name": "p_1_u.lua.arcx",
            "hash": "ad53c06da75a60e66f69c13efb4299a8",
            "version": 113
        },
        "lua.json": {
            "file_name": "lua.json",
            "hash": "f48f613cb47b0300d718686874b99e53",
            "version": 109
        },
        "p_1_u.data.arcx": {
            "file_name": "p_1_u.data.arcx",
            "hash": "0316f7285af4549698b8b8e3c3afec32",
            "version": 113
        }
    }
}